LICENSE
README.rst
setup.cfg
setup.py
AristaLibrary/AristaLibrary.py
AristaLibrary/Expect.py
AristaLibrary/__init__.py
AristaLibrary/version.py
docs/AristaLibrary.html
robotframework_aristalibrary.egg-info/PKG-INFO
robotframework_aristalibrary.egg-info/SOURCES.txt
robotframework_aristalibrary.egg-info/dependency_links.txt
robotframework_aristalibrary.egg-info/requires.txt
robotframework_aristalibrary.egg-info/top_level.txt