Metadata-Version: 1.1
Name: robotframework-aristalibrary
Version: 1.2.0
Summary: Python Robot Framework Library for EOS devices
Home-page: https://aristanetworks.github.io/robotframework-aristalibrary/
Author: Arista EOS+ Consulting Services
Author-email: eosplus-dev@arista.com
License: BSD-3
Download-URL: https://github.com/aristanetworks/robotframework-aristalibrary/tarball/1.2.0
Keywords: robotframework testing testautomation arista eos eapi pyeapi
Platform: any
